vitessestack_common/__init__.py
vitessestack_common/event.py
vitessestack_common/response.py
vitessestack_common/router.py
vitessestack_common/test.py
vitessestack_common/updates.py
vitessestack_common/utils.py
vitessestack_common/gateway/__init__.py
vitessestack_common/gateway/utils.py
vitessestack_common-0.0.6.dist-info/LICENSE
vitessestack_common-0.0.6.dist-info/METADATA
vitessestack_common-0.0.6.dist-info/WHEEL
vitessestack_common-0.0.6.dist-info/top_level.txt
vitessestack_common-0.0.6.dist-info/RECORD
