Metadata-Version: 2.1
Name: vitessestack-common
Version: 0.0.6
Summary: Common libraries for Vitessestack APIs
Home-page: https://github.com/VitessestackTech/APICommons
Author: Santiago Melo Medina
Author-email: smelomedina05@gmail.com
Classifier: Programming Language :: Python :: 3
Classifier: License :: OSI Approved :: MIT License
Classifier: Operating System :: OS Independent
Requires-Python: >=3.11
License-File: LICENSE
Requires-Dist: pypdf
Requires-Dist: pillow
Requires-Dist: reportlab
Requires-Dist: pydantic==1.8.0
Requires-Dist: pyjwt==2.10.1
Requires-Dist: pymongo==4.10.1
Requires-Dist: boto3==1.35.81
Requires-Dist: requests==2.32.3
Requires-Dist: redis==5.2.1
Requires-Dist: cryptography==38.0.3
Requires-Dist: flask
Requires-Dist: python-dotenv
